README.md
setup.py
pubMunch/__init__.py
pubMunch/htmlPrint.py
pubMunch/maxCommon.py
pubMunch/maxTables.py
pubMunch/maxWeb.py
pubMunch/maxXml.py
pubMunch/pubConf.py
pubMunch/pubCrawlLib.py
pubMunch/pubCrossRef.py
pubMunch/pubGeneric.py
pubMunch/pubPubmed.py
pubMunch/pubStore.py
pubMunch/unicodeConvert.py
pubMunch/data/journals.tab
pubMunch/data/tandfIssns.txt
pubMunch/scihub/__init__.py
pubMunch/scihub/scihub.py
pubMunch3.egg-info/PKG-INFO
pubMunch3.egg-info/SOURCES.txt
pubMunch3.egg-info/dependency_links.txt
pubMunch3.egg-info/entry_points.txt
pubMunch3.egg-info/requires.txt
pubMunch3.egg-info/top_level.txt