Metadata-Version: 1.0
Name: pubMunch3
Version: 1.0.4
Summary: A library and tool for downloading pubmed articles
Home-page: UNKNOWN
Author: UNKNOWN
Author-email: UNKNOWN
License: UNKNOWN
Platform: UNKNOWN
